[
  { "abbr": "ACL",     "name": "Atlantic Coast Line",                        "price": 12000 },
  { "abbr": "AT&SF",   "name": "Atchison, Topeka, and Santa Fe RR",          "price": 40000 },
  { "abbr": "B&M",     "name": "Boston and Maine RR",                        "price": 4000  },
  { "abbr": "B&O",     "name": "Baltimore and Ohio",                         "price": 24000 },
  { "abbr": "C&NW",    "name": "Chicago and NorthWestern RR",                "price": 14000 },
  { "abbr": "C&O",     "name": "Chesapeake and Ohio",                        "price": 20000 },
  { "abbr": "CB&Q",    "name": "Chicago, Burlington, and Quincy",            "price": 20000 },
  { "abbr": "CMStP&P", "name": "Chicago, Milwaukee, St. Paul, and Pacific",  "price": 18000 },
  { "abbr": "CRI&P",   "name": "Chicago, Rock Island, and Pacific",          "price": 29000 },
  { "abbr": "D&RGW",   "name": "Denver and Rio Grande Western",              "price": 6000  },
  { "abbr": "GM&O",    "name": "Gulf, Mobile, and Ohio",                     "price": 12000 },
  { "abbr": "GN",      "name": "Great Northern",                             "price": 17000 },
  { "abbr": "IC",      "name": "Illinois Central RR",                        "price": 14000 },
  { "abbr": "L&N",     "name": "Louisville and Nashville",                   "price": 18000 },
  { "abbr": "MP",      "name": "Missouri Pacific",                           "price": 21000 },
  { "abbr": "N&W",     "name": "Norfolk and Western",                        "price": 12000 },
  { "abbr": "NP",      "name": "Northern Pacific",                           "price": 14000 },
  { "abbr": "NYC",     "name": "New York Central",                           "price": 28000 },
  { "abbr": "NYNH&H",  "name": "New York, New Haven, and Hartford RR",       "price": 4000  },
  { "abbr": "PA",      "name": "Pennsylvania RR",                            "price": 30000 },
  { "abbr": "RF&P",    "name": "Richmond, Fredericksburg, and Potomac RR",   "price": 4000  },
  { "abbr": "SAL",     "name": "Seaboard Airline RR",                        "price": 14000 },
  { "abbr": "SLSF",    "name": "St. Louis and San Francisco",                "price": 19000 },
  { "abbr": "SOU",     "name": "Southern Railway",                           "price": 20000 },
  { "abbr": "SP",      "name": "Southern Pacific",                           "price": 42000 },
  { "abbr": "T&P",     "name": "Texas and Pacific",                          "price": 10000 },
  { "abbr": "UP",      "name": "Union Pacific",                              "price": 40000 },
  { "abbr": "WP",      "name": "Western Pacific",                            "price": 8000  }
]
